hashycalls/__init__.py
hashycalls/__main__.py
hashycalls/args.py
hashycalls/cli.py
hashycalls/colors.py
hashycalls/core.py
hashycalls/rsrc/code/solution file/.editorconfig
hashycalls/rsrc/code/solution file/hashycalls.sln
hashycalls/rsrc/code/solution file/proj/hashycalls.vcxproj
hashycalls/rsrc/code/solution file/proj/hashycalls.vcxproj.filters
hashycalls/rsrc/code/solution file/proj/hashycalls.vcxproj.user
hashycalls/rsrc/code/solution file/src/hashycalls.c
hashycalls/rsrc/code/solution file/src/hashycalls.h
hashycalls/rsrc/code/solution file/src/main.c
hashycalls/rsrc/code/templates/djb2.c
hashycalls/rsrc/code/templates/murmur.c
hashycalls/rsrc/data/name-conversion.json
hashycalls/rsrc/data/type-conversion.json
hashycalls/rsrc/data/winapi.json
hashycalls-2.1.1.dist-info/METADATA
hashycalls-2.1.1.dist-info/WHEEL
hashycalls-2.1.1.dist-info/entry_points.txt
hashycalls-2.1.1.dist-info/RECORD
