Metadata-Version: 2.4
Name: hashycalls
Version: 2.1.1
Summary: An Import Address Table obfuscation utility for C/C++ based windows implants
Project-URL: Github, https://github.com/wizardy0ga/hashycalls
Project-URL: Source, https://github.com/wizardy0ga/Hashycalls/tree/master/src/hashycalls
Project-URL: Documentation, https://github.com/wizardy0ga/Hashycalls/tree/master/docs/en
Author: wizardy0ga
Requires-Python: >=3.10
